librebound.cp312-win32.pyd
rebound/__init__.py
rebound/binary_field_descriptor.py
rebound/citations.py
rebound/data.py
rebound/hash.py
rebound/horizons.py
rebound/orbit.py
rebound/particle.py
rebound/particles.py
rebound/plotting.py
rebound/rebound.h
rebound/rotation.py
rebound/simulation.py
rebound/simulationarchive.py
rebound/tools.py
rebound/units.py
rebound/variation.py
rebound/vectors.py
rebound/widget.py
rebound/integrators/__init__.py
rebound/integrators/bs.py
rebound/integrators/eos.py
rebound/integrators/ias15.py
rebound/integrators/janus.py
rebound/integrators/mercurius.py
rebound/integrators/saba.py
rebound/integrators/sei.py
rebound/integrators/trace.py
rebound/integrators/whfast.py
rebound/integrators/whfast512.py
rebound-4.4.11.dist-info/licenses/LICENSE
rebound-4.4.11.dist-info/METADATA
rebound-4.4.11.dist-info/WHEEL
rebound-4.4.11.dist-info/top_level.txt
rebound-4.4.11.dist-info/RECORD
