Metadata-Version: 2.4
Name: rebound
Version: 4.4.11
Summary: An open-source multi-purpose N-body code
Home-page: https://github.com/hannorein/rebound/
Author: Hanno Rein
Author-email: hanno@hanno-rein.de
License: GPL
Keywords: astronomy astrophysics nbody integrator symplectic wisdom-holman
Classifier: Development Status :: 5 - Production/Stable
Classifier: Intended Audience :: Science/Research
Classifier: Intended Audience :: Developers
Classifier: Topic :: Software Development :: Build Tools
Classifier: Topic :: Scientific/Engineering :: Astronomy
Classifier: License :: OSI Approved :: GNU General Public License v3 or later (GPLv3+)
Classifier: Programming Language :: Python :: 2
Classifier: Programming Language :: Python :: 3
License-File: LICENSE
Dynamic: author
Dynamic: author-email
Dynamic: classifier
Dynamic: description
Dynamic: description-content-type
Dynamic: home-page
Dynamic: keywords
Dynamic: license
Dynamic: license-file
Dynamic: summary
